pgslice/__init__.py
pgslice/__main__.py
pgslice/cli.py
pgslice/config.py
pgslice/repl.py
pgslice/cache/__init__.py
pgslice/cache/schema_cache.py
pgslice/db/__init__.py
pgslice/db/connection.py
pgslice/db/schema.py
pgslice/dumper/__init__.py
pgslice/dumper/ddl_generator.py
pgslice/dumper/dependency_sorter.py
pgslice/dumper/dump_service.py
pgslice/dumper/sql_generator.py
pgslice/dumper/writer.py
pgslice/graph/__init__.py
pgslice/graph/models.py
pgslice/graph/traverser.py
pgslice/graph/visited_tracker.py
pgslice/operations/__init__.py
pgslice/operations/dump_ops.py
pgslice/operations/parsing.py
pgslice/operations/schema_ops.py
pgslice/utils/__init__.py
pgslice/utils/exceptions.py
pgslice/utils/graph_visualizer.py
pgslice/utils/logging_config.py
pgslice/utils/security.py
pgslice/utils/spinner.py
pgslice-0.2.5.dist-info/licenses/LICENSE
pgslice-0.2.5.dist-info/METADATA
pgslice-0.2.5.dist-info/WHEEL
pgslice-0.2.5.dist-info/entry_points.txt
pgslice-0.2.5.dist-info/top_level.txt
pgslice-0.2.5.dist-info/RECORD
