Metadata-Version: 2.4
Name: pgslice
Version: 0.2.5
Summary: Extract PostgreSQL records with all related data via FK relationships
Author-email: Your Name <your.email@example.com>
License: MIT
Classifier: Development Status :: 3 - Alpha
Classifier: Intended Audience :: Developers
Classifier: License :: OSI Approved :: MIT License
Classifier: Programming Language :: Python :: 3
Classifier: Programming Language :: Python :: 3.10
Classifier: Programming Language :: Python :: 3.11
Classifier: Programming Language :: Python :: 3.12
Classifier: Programming Language :: Python :: 3.13
Classifier: Programming Language :: Python :: 3.14
Requires-Python: >=3.10
License-File: LICENSE
Requires-Dist: psycopg[binary]>=3.2.2
Requires-Dist: prompt-toolkit>=3.0.0
Requires-Dist: printy==3.0.1
Requires-Dist: tabulate>=0.9.0
Requires-Dist: python-dotenv>=1.0.0
Requires-Dist: tqdm>=4.66.0
Provides-Extra: dev
Requires-Dist: pytest>=7.4.0; extra == "dev"
Requires-Dist: pytest-cov>=4.1.0; extra == "dev"
Requires-Dist: pytest-mock>=3.11.0; extra == "dev"
Requires-Dist: pytest-asyncio>=0.21.0; extra == "dev"
Requires-Dist: pytest-xdist>=3.5.0; extra == "dev"
Requires-Dist: mypy>=1.5.0; extra == "dev"
Requires-Dist: ruff>=0.1.0; extra == "dev"
Requires-Dist: freezegun>=1.2.0; extra == "dev"
Requires-Dist: Faker>=20.0.0; extra == "dev"
Requires-Dist: pre-commit>=3.0.0; extra == "dev"
Dynamic: license-file
